marine/__init__.py
marine/logger.py
marine/predict.py
marine/visualize_diff.py
marine/bin/__init__.py
marine/bin/build_vocab.py
marine/bin/jsut2corpus.py
marine/bin/make_raw_corpus.py
marine/bin/pack_corpus.py
marine/bin/prepare_features_pyopenjtalk.py
marine/bin/test.py
marine/bin/train.py
marine/bin/conf/train/__init__.py
marine/bin/conf/train/config.yaml
marine/bin/conf/train/criterions/__init__.py
marine/bin/conf/train/criterions/att-mtl.yaml
marine/bin/conf/train/criterions/crf-mtl.yaml
marine/bin/conf/train/criterions/linear-att-mtl.yaml
marine/bin/conf/train/data/__init__.py
marine/bin/conf/train/data/ap.yaml
marine/bin/conf/train/data/binary.yaml
marine/bin/conf/train/data/simple.yaml
marine/bin/conf/train/model/__init__.py
marine/bin/conf/train/model/att-mtl.yaml
marine/bin/conf/train/model/crf-mtl.yaml
marine/bin/conf/train/model/linear-att-mtl.yaml
marine/bin/conf/train/optim/__init__.py
marine/bin/conf/train/optim/adam_plate.yaml
marine/bin/conf/train/train/__init__.py
marine/bin/conf/train/train/local.yaml
marine/criterions/__init__.py
marine/criterions/crossentopyloss.py
marine/criterions/log_likelihood.py
marine/data/__init__.py
marine/data/dataset.py
marine/data/jtalk_dict.py
marine/data/pad.py
marine/data/util.py
marine/data/feature/__init__.py
marine/data/feature/feature_set.py
marine/data/feature/feature_table.py
marine/dict/accent_phrase_boundary/artifact.tsv
marine/dict/accent_status/artifact.tsv
marine/models/__init__.py
marine/models/att_lstm_decoder.py
marine/models/base_model.py
marine/models/bilstm_encoder.py
marine/models/crf_decoder.py
marine/models/embedding.py
marine/models/linear_decoder.py
marine/models/util.py
marine/modules/__init__.py
marine/modules/attention.py
marine/modules/crf_tagger.py
marine/utils/__init__.py
marine/utils/metrics.py
marine/utils/openjtalk_util.py
marine/utils/post_process.py
marine/utils/pretrained.py
marine/utils/regex.py
marine/utils/util.py
marine/utils/g2p_util/__init__.py
marine/utils/g2p_util/accent.py
marine_plus-0.0.6.post3.dist-info/LICENSE
marine_plus-0.0.6.post3.dist-info/METADATA
marine_plus-0.0.6.post3.dist-info/WHEEL
marine_plus-0.0.6.post3.dist-info/entry_points.txt
marine_plus-0.0.6.post3.dist-info/top_level.txt
marine_plus-0.0.6.post3.dist-info/RECORD
