Metadata-Version: 2.1
Name: marine-plus
Version: 0.0.6.post3
Summary: Marine: Multi-task learning based on Japanese accent estimation (Also supports Windows and Python 3.12)
Author: Byeongseon Park
Author-email: 6gsn.park@gmail.com
Classifier: Operating System :: Unix
Classifier: Operating System :: MacOS
Classifier: Programming Language :: Python
Classifier: Programming Language :: Python :: 3
Classifier: Programming Language :: Python :: 3.8
Classifier: Programming Language :: Python :: 3.9
Classifier: Programming Language :: Python :: 3.10
Classifier: Programming Language :: Python :: 3.11
Classifier: Programming Language :: Python :: 3.12
Classifier: License :: OSI Approved :: Apache Software License
Classifier: Topic :: Scientific/Engineering
Classifier: Topic :: Software Development
Classifier: Intended Audience :: Science/Research
Classifier: Intended Audience :: Developers
License-File: LICENSE
Requires-Dist: numpy<2,>=1.21.0
Requires-Dist: torch>=1.7.0
Requires-Dist: hydra-core>=1.1.0
Requires-Dist: hydra-colorlog>=1.1.0
Requires-Dist: tqdm
Requires-Dist: joblib
Requires-Dist: pykakasi>=2.3.0
Requires-Dist: importlib-resources; python_version < "3.9"
Provides-Extra: dev
Requires-Dist: torchmetrics; extra == "dev"
Requires-Dist: scikit-learn; extra == "dev"
Requires-Dist: docstr-coverage; extra == "dev"
Requires-Dist: tensorboard; extra == "dev"
Requires-Dist: matplotlib; extra == "dev"
Requires-Dist: pytest; extra == "dev"
Requires-Dist: pytest-cov; extra == "dev"
Requires-Dist: pysen; extra == "dev"
Requires-Dist: black>=19.19b0; extra == "dev"
Requires-Dist: flake8>=3.7; extra == "dev"
Requires-Dist: flake8-bugbear; extra == "dev"
Requires-Dist: isort>=4.3; extra == "dev"
Requires-Dist: click; extra == "dev"
Provides-Extra: docs
Requires-Dist: sphinx; extra == "docs"
Requires-Dist: sphinx-autobuild; extra == "docs"
Requires-Dist: sphinx-rtd-theme; extra == "docs"
Requires-Dist: nbsphinx>=0.8.6; extra == "docs"
Requires-Dist: Jinja2>=3.0.1; extra == "docs"
Requires-Dist: pandoc; extra == "docs"
Requires-Dist: ipython; extra == "docs"
Requires-Dist: jupyter; extra == "docs"
Provides-Extra: pyopenjtalk
Requires-Dist: pyopenjtalk-plus; extra == "pyopenjtalk"
